{ 
  "world_name" : "Chart",
  "valid_task" : ["Loop"],
  "task": {
    "Delivery": {
    },
    "Loop": {
      "places": [
        "CSSD_Room",
        "CSSD_mir_01",
        "CSSD_mir_02",
        "MiR_ClinicArea",
        "MiR_enterParking_01",
        "MiR_Parking_01",
        "MiR_LiftArea",
        "MiR_enterParking_02",
        "MiR_Parking_02",
        "MiR_enter_OT",
        "OT_Room",
        "Consult_Room",
        "RoMiO_ClinicArea",
        "RoMiO_enterParking_01",
        "RoMiO_Parking_01",
        "RoMiO_enter_WardArea",
        "RoMiO_enterParking_02]",
        "RoMiO_Parking_02",
        "RoMiO_WardArea",
        "MissyBot_ClinicArea",
        "MissyBot_enterParking_01",
        "MissyBot_Parking_01",
        "MissyBot_WardArea",
        "Sesto_ClinicArea",
        "Sesto_enterParking_01",
        "Sesto_Parking_01",
        "Sesto_LiftArea_01",
        "Sesto_LiftArea_02",
        "Sesto_enterParking_02",
        "Sesto_Parking_02",
        "Sesto_OT_Area",
        "A&E_Area",
        "TrolleyBed_CSSD",
        "TrolleyBed_enterCSSD",
        "TrolleyBed_LiftArea",
        "TrolleyBed_enter_OT",
        "TrolleyBed_OT",
        "TrolleyBed_Turn",
        "TrolleyBed_ClinicArea"    
     ]
    },
    "Clean": {
    },
    "Station": {
    },
    "Patrol": {
    },
    "Charging": {
    }
  }
}
